{"name":"irish-road-system","title":"Irish Road System","description":"Irish Road System","licenses":[{"url":"https://creativecommons.org/licenses/by/4.0/","title":"Creative Commons Attribution 4.0"}],"publishers":[{"name":null,"web":null}],"resources":[{"name":"Irish Road System A","mediatype":"text/csv","description":"","path":"data/irish-road-system-a.dbf"},{"name":"Irish Road System B","mediatype":"text/csv","description":"","path":"data/irish-road-system-b.shp"},{"name":"Irish Road System C","mediatype":"text/csv","description":"","path":"data/irish-road-system-c.shx"},{"name":"Irish Road System D","mediatype":"text/csv","description":"","path":"data/irish-road-system-d.prj"},{"name":"irish-road-system","mediatype":"text/csv","description":"irish-road-system","path":"data/irish-road-system.geojson"}]}